loglu_tensorflow/__init__.py
loglu_tensorflow/loglu_tensorflow.py
loglu_tensorflow-0.0.1.dist-info/METADATA
loglu_tensorflow-0.0.1.dist-info/WHEEL
loglu_tensorflow-0.0.1.dist-info/top_level.txt
loglu_tensorflow-0.0.1.dist-info/RECORD
