Metadata-Version: 2.1
Name: loglu-tensorflow
Version: 0.0.1
Summary: LogLU Activation Function - TensorFlow
Home-page: https://github.com/XenReZ/LogLU-TensorFlow
Author: Rishi Chaitanya
Author-email: rishichaitanya888@gmail.com
License: Apache-2.0
Classifier: Programming Language :: Python :: 3
Classifier: License :: OSI Approved :: Apache Software License
Classifier: Operating System :: OS Independent
Classifier: Intended Audience :: Developers
Classifier: Intended Audience :: Science/Research
Classifier: Topic :: Scientific/Engineering :: Artificial Intelligence
Requires-Python: >=3.6
Requires-Dist: tensorflow>=2.10.0
Requires-Dist: keras>=2.10.0
